setup.py
django_simple_location_field2/__init__.py
django_simple_location_field2/fields.py
django_simple_location_field2/location.py
django_simple_location_field2.egg-info/PKG-INFO
django_simple_location_field2.egg-info/SOURCES.txt
django_simple_location_field2.egg-info/dependency_links.txt
django_simple_location_field2.egg-info/top_level.txt