Metadata-Version: 1.0
Name: django-simple-location-field2
Version: 1.0.0
Summary: Simple field for django
Home-page: UNKNOWN
Author: Yosa Rem
Author-email: ilya.solomein@gmail.com
License: UNKNOWN
Platform: UNKNOWN
